rollin_lxd/__init__.py
rollin_lxd-0.10.0.data/scripts/rollin-lxd
rollin_lxd-0.10.0.dist-info/LICENSE
rollin_lxd-0.10.0.dist-info/METADATA
rollin_lxd-0.10.0.dist-info/WHEEL
rollin_lxd-0.10.0.dist-info/top_level.txt
rollin_lxd-0.10.0.dist-info/RECORD
