Metadata-Version: 2.1
Name: rollin-lxd
Version: 0.10.0
Summary: LXD dynamic management based on kivalu
Home-page: https://zebr0.io/projects/rollin/lxd
Download-URL: https://github.com/zebr0/rollin-lxd
Author: Thomas JOUANNOT
Author-email: mazerty@gmail.com
License: MIT
Classifier: Development Status :: 4 - Beta
Classifier: Environment :: Console
Classifier: Intended Audience :: Developers
Classifier: Intended Audience :: Information Technology
Classifier: Intended Audience :: System Administrators
Classifier: License :: OSI Approved :: MIT License
Classifier: Natural Language :: English
Classifier: Operating System :: POSIX
Classifier: Programming Language :: Python :: 3
Classifier: Topic :: System
License-File: LICENSE
Requires-Dist: kivalu
Requires-Dist: PyYAML
Requires-Dist: requests-unixsocket
